devfacPyLogger/__init__.py
devfacPyLogger-0.2.1.dist-info/LICENSE
devfacPyLogger-0.2.1.dist-info/METADATA
devfacPyLogger-0.2.1.dist-info/WHEEL
devfacPyLogger-0.2.1.dist-info/top_level.txt
devfacPyLogger-0.2.1.dist-info/RECORD
