Metadata-Version: 2.1
Name: devfacPyLogger
Version: 0.2.1
Summary: Simple, Colored, File and Line number printable logger
Home-page: https://github.com/transpine/devfacPyLogger
Author: transpine
Author-email: transpine@gmail.com
License: MIT
Platform: UNKNOWN
Classifier: Programming Language :: Python :: 3
Classifier: License :: OSI Approved :: MIT License
Classifier: Operating System :: OS Independent
Requires-Dist: colorlog
Requires-Dist: ipython
